masakariclient/__init__.py
masakariclient/api_versions.py
masakariclient/plugin.py
masakariclient/common/__init__.py
masakariclient/common/exception.py
masakariclient/common/i18n.py
masakariclient/common/utils.py
masakariclient/osc/__init__.py
masakariclient/osc/v1/__init__.py
masakariclient/osc/v1/host.py
masakariclient/osc/v1/notification.py
masakariclient/osc/v1/segment.py
masakariclient/osc/v1/vmove.py
masakariclient/tests/__init__.py
masakariclient/tests/base.py
masakariclient/tests/unit/__init__.py
masakariclient/tests/unit/osc/__init__.py
masakariclient/tests/unit/osc/v1/__init__.py
masakariclient/tests/unit/osc/v1/test_host.py
masakariclient/tests/unit/osc/v1/test_notification.py
masakariclient/tests/unit/osc/v1/test_segment.py
masakariclient/tests/unit/osc/v1/test_vmove.py
python_masakariclient-8.7.0.dist-info/AUTHORS
python_masakariclient-8.7.0.dist-info/LICENSE
python_masakariclient-8.7.0.dist-info/METADATA
python_masakariclient-8.7.0.dist-info/WHEEL
python_masakariclient-8.7.0.dist-info/entry_points.txt
python_masakariclient-8.7.0.dist-info/pbr.json
python_masakariclient-8.7.0.dist-info/top_level.txt
python_masakariclient-8.7.0.dist-info/RECORD
