Metadata-Version: 2.1
Name: python-masakariclient
Version: 8.7.0
Summary: masakariclient module and a CLI tool for masakari
Home-page: https://docs.openstack.org/python-masakariclient/latest/
Author: OpenStack
Author-email: openstack-discuss@lists.openstack.org
Classifier: Environment :: OpenStack
Classifier: Intended Audience :: Information Technology
Classifier: Intended Audience :: System Administrators
Classifier: License :: OSI Approved :: Apache Software License
Classifier: Operating System :: POSIX :: Linux
Classifier: Programming Language :: Python
Classifier: Programming Language :: Python :: Implementation :: CPython
Classifier: Programming Language :: Python :: 3 :: Only
Classifier: Programming Language :: Python :: 3
Classifier: Programming Language :: Python :: 3.8
Classifier: Programming Language :: Python :: 3.9
Classifier: Programming Language :: Python :: 3.10
Classifier: Programming Language :: Python :: 3.11
Requires-Python: >=3.8
License-File: LICENSE
License-File: AUTHORS
Requires-Dist: openstacksdk >=0.13.0
Requires-Dist: osc-lib >=1.8.0
Requires-Dist: oslo.i18n >=3.15.3
Requires-Dist: oslo.serialization !=2.19.1,>=2.18.0
Requires-Dist: pbr !=2.1.0,>=2.0.0
